WordsPy/Helpers.py
WordsPy/Language.py
WordsPy/__init__.py
WordsPy/main.py
WordsPy-2.0.0.dist-info/METADATA
WordsPy-2.0.0.dist-info/WHEEL
WordsPy-2.0.0.dist-info/top_level.txt
WordsPy-2.0.0.dist-info/RECORD
