Metadata-Version: 2.1
Name: WordsPy
Version: 2.0.0
Summary: Get words for any langauge.
Author: eymenefealtun (Eymen Efe Altun)
Author-email: <eymenefealtun@hotmail.com>
Keywords: python,words,extraction,word,lexicon
Classifier: Development Status :: 1 - Planning
Classifier: Intended Audience :: Developers
Classifier: Programming Language :: Python :: 3
Classifier: Operating System :: Unix
Classifier: Operating System :: MacOS :: MacOS X
Classifier: Operating System :: Microsoft :: Windows
Requires-Dist: requests
